odoo/addons/mail_outbound_static/README.rst
odoo/addons/mail_outbound_static/__init__.py
odoo/addons/mail_outbound_static/__manifest__.py
odoo/addons/mail_outbound_static/i18n/mail_outbound_static.pot
odoo/addons/mail_outbound_static/models/__init__.py
odoo/addons/mail_outbound_static/models/ir_mail_server.py
odoo/addons/mail_outbound_static/readme/CONTRIBUTORS.rst
odoo/addons/mail_outbound_static/readme/DESCRIPTION.rst
odoo/addons/mail_outbound_static/readme/ROADMAP.rst
odoo/addons/mail_outbound_static/readme/USAGE.rst
odoo/addons/mail_outbound_static/static/description/icon.png
odoo/addons/mail_outbound_static/static/description/index.html
odoo/addons/mail_outbound_static/tests/__init__.py
odoo/addons/mail_outbound_static/tests/test.msg
odoo/addons/mail_outbound_static/tests/test_ir_mail_server.py
odoo/addons/mail_outbound_static/views/ir_mail_server_view.xml
odoo11_addon_mail_outbound_static-11.0.1.0.0.99.dev3.dist-info/METADATA
odoo11_addon_mail_outbound_static-11.0.1.0.0.99.dev3.dist-info/WHEEL
odoo11_addon_mail_outbound_static-11.0.1.0.0.99.dev3.dist-info/top_level.txt
odoo11_addon_mail_outbound_static-11.0.1.0.0.99.dev3.dist-info/RECORD
